{
	"format_version": "1.21.6",
	"credit": "Made with Blockbench",
	"texture_size": [225, 950],
	"textures": {
		"0": "yte:block/metal",
		"3": "yte:block/steel",
		"4": "yte:block/1",
		"particle": "yte:block/metal"
	},
	"elements": [
		{
			"from": [13.4, 9.525, 0],
			"to": [16, 12.025, 0.1],
			"rotation": {"angle": 0, "axis": "y", "origin": [7.875, 6.125, 0]},
			"faces": {
				"north": {"uv": [0, 1.43459, 12.76429, 6.33308], "texture": "#0"},
				"south": {"uv": [3.00952, 0, 8.41396, 16], "texture": "#0"},
				"up": {"uv": [4.45714, 1.16278, 16, 0.73985], "texture": "#0"},
				"down": {"uv": [1.33333, 0.66767, 16, 1.33835], "texture": "#0"}
			}
		},
		{
			"from": [10.1175, 9.9075, 0.1],
			"to": [10.2425, 10.1575, 0.25],
			"rotation": {"angle": 22.5, "axis": "z", "origin": [7.125, 19.025, 0.1]},
			"faces": {
				"north": {"uv": [0, 1.43459, 12.76429, 6.33308], "rotation": 270, "texture": "#4"},
				"south": {"uv": [0.78222, 0.52211, 2.20444, 0.85895], "rotation": 90, "texture": "#4"},
				"up": {"uv": [0, 8.42105, 1.0621, 15.15789], "rotation": 90, "texture": "#4"}
			}
		},
		{
			"from": [13.6725, 19.06, 0.1],
			"to": [13.9225, 19.185, 0.25],
			"rotation": {"angle": -45, "axis": "z", "origin": [4.775, 16.05, 0.1]},
			"faces": {
				"north": {"uv": [0, 1.43459, 12.76429, 6.33308], "texture": "#4"},
				"south": {"uv": [0.78222, 0.52211, 2.20444, 0.85895], "texture": "#4"},
				"west": {"uv": [0, 8.42105, 1.0621, 15.15789], "texture": "#4"}
			}
		},
		{
			"from": [9.64, 9.0475, 0.1],
			"to": [9.765, 9.2975, 0.25],
			"rotation": {"angle": -22.5, "axis": "z", "origin": [12.775, 0.15, 0.1]},
			"faces": {
				"north": {"uv": [0, 1.43459, 12.76429, 6.33308], "rotation": 90, "texture": "#4"},
				"south": {"uv": [0.78222, 15.66316, 2.20444, 16], "rotation": 270, "texture": "#4"},
				"down": {"uv": [0, 8.42105, 1.0621, 15.15789], "rotation": 270, "texture": "#4"}
			}
		},
		{
			"from": [18.0225, 4.16, 0.1],
			"to": [18.2725, 4.285, 0.25],
			"rotation": {"angle": 45, "axis": "z", "origin": [9.125, 1.15, 0.1]},
			"faces": {
				"north": {"uv": [0, 1.43459, 12.76429, 6.33308], "texture": "#4"},
				"south": {"uv": [0.78222, 15.66316, 2.20444, 16], "texture": "#4"},
				"west": {"uv": [0, 8.42105, 1.0621, 15.15789], "texture": "#4"}
			}
		},
		{
			"from": [15.02, 6.5025, 0.1],
			"to": [15.27, 6.6275, 0.25],
			"rotation": {"angle": 22.5, "axis": "z", "origin": [6.175, 3.5, 0.1]},
			"faces": {
				"north": {"uv": [0, 1.43459, 12.76429, 6.33308], "texture": "#4"},
				"south": {"uv": [0.78222, 15.66316, 2.20444, 16], "texture": "#4"},
				"west": {"uv": [0, 8.42105, 1.0621, 15.15789], "texture": "#4"}
			}
		},
		{
			"from": [12.675, 15.41, 0.1],
			"to": [12.925, 15.535, 0.25],
			"rotation": {"angle": -22.5, "axis": "z", "origin": [3.775, 12.4, 0.1]},
			"faces": {
				"north": {"uv": [0, 1.43459, 12.76429, 6.33308], "texture": "#4"},
				"south": {"uv": [0.78222, 0.52211, 2.20444, 0.85895], "texture": "#4"},
				"west": {"uv": [0, 8.42105, 1.0621, 15.15789], "texture": "#4"}
			}
		},
		{
			"from": [13.15, 9.775, 0.1],
			"to": [13.4, 11.775, 0.25],
			"rotation": {"angle": 0, "axis": "y", "origin": [4.275, 6.125, 0.1]},
			"faces": {
				"north": {"uv": [0, 1.43459, 12.76429, 6.33308], "texture": "#4"},
				"south": {"uv": [0.7619, 0.42105, 2.97143, 15.57895], "texture": "#4"},
				"west": {"uv": [0, 0.42105, 1.05953, 15.57895], "texture": "#4"},
				"down": {"uv": [1.33333, 0.66767, 16, 1.33835], "texture": "#4"}
			}
		},
		{
			"from": [13.4, 9.525, 0.1],
			"to": [16, 12.025, 0.25],
			"rotation": {"angle": 0, "axis": "y", "origin": [7.875, 6.125, 0.1]},
			"faces": {
				"north": {"uv": [0, 1.43459, 12.76429, 6.33308], "texture": "#4"},
				"south": {"uv": [3.00952, 0, 8.41396, 16], "texture": "#4"},
				"up": {"uv": [4.45714, 1.16278, 10.21714, 0.73985], "texture": "#4"},
				"down": {"uv": [4.45714, 1.16278, 10.21714, 0.73985], "texture": "#4"}
			}
		},
		{
			"from": [13.15, 9.775, 0],
			"to": [13.4, 11.775, 0.1],
			"rotation": {"angle": 0, "axis": "y", "origin": [4.275, 6.125, 0]},
			"faces": {
				"north": {"uv": [0, 1.43459, 12.76429, 6.33308], "texture": "#0"},
				"south": {"uv": [0.7619, 0.42105, 2.97143, 15.57895], "texture": "#0"},
				"west": {"uv": [0, 0.42105, 1.05953, 15.57895], "texture": "#0"},
				"down": {"uv": [1.33333, 0.66767, 16, 1.33835], "texture": "#0"}
			}
		},
		{
			"from": [12.675, 15.41, 0],
			"to": [12.925, 15.535, 0.1],
			"rotation": {"angle": -22.5, "axis": "z", "origin": [3.775, 12.4, 0]},
			"faces": {
				"north": {"uv": [0, 1.43459, 12.76429, 6.33308], "texture": "#0"},
				"south": {"uv": [0.78222, 0.52211, 2.20444, 0.85895], "texture": "#0"},
				"west": {"uv": [0, 8.42105, 1.0621, 15.15789], "texture": "#0"}
			}
		},
		{
			"from": [15.02, 6.5025, 0],
			"to": [15.27, 6.6275, 0.1],
			"rotation": {"angle": 22.5, "axis": "z", "origin": [6.175, 3.5, 0]},
			"faces": {
				"north": {"uv": [0, 1.43459, 12.76429, 6.33308], "texture": "#0"},
				"south": {"uv": [0.78222, 15.66316, 2.20444, 16], "texture": "#0"},
				"west": {"uv": [0, 8.42105, 1.0621, 15.15789], "texture": "#0"}
			}
		},
		{
			"from": [18.0225, 4.16, 0],
			"to": [18.2725, 4.285, 0.1],
			"rotation": {"angle": 45, "axis": "z", "origin": [9.125, 1.15, 0]},
			"faces": {
				"north": {"uv": [0, 1.43459, 12.76429, 6.33308], "texture": "#0"},
				"south": {"uv": [0.78222, 15.66316, 2.20444, 16], "texture": "#0"},
				"west": {"uv": [0, 8.42105, 1.0621, 15.15789], "texture": "#0"}
			}
		},
		{
			"from": [9.64, 9.0475, 0],
			"to": [9.765, 9.2975, 0.1],
			"rotation": {"angle": -22.5, "axis": "z", "origin": [12.775, 0.15, 0]},
			"faces": {
				"north": {"uv": [0, 1.43459, 12.76429, 6.33308], "rotation": 90, "texture": "#0"},
				"south": {"uv": [0.78222, 15.66316, 2.20444, 16], "rotation": 270, "texture": "#0"},
				"down": {"uv": [0, 8.42105, 1.0621, 15.15789], "rotation": 270, "texture": "#0"}
			}
		},
		{
			"from": [13.6725, 19.06, 0],
			"to": [13.9225, 19.185, 0.1],
			"rotation": {"angle": -45, "axis": "z", "origin": [4.775, 16.05, 0]},
			"faces": {
				"north": {"uv": [0, 1.43459, 12.76429, 6.33308], "texture": "#0"},
				"south": {"uv": [0.78222, 0.52211, 2.20444, 0.85895], "texture": "#0"},
				"west": {"uv": [0, 8.42105, 1.0621, 15.15789], "texture": "#0"}
			}
		},
		{
			"from": [10.1175, 9.9075, 0],
			"to": [10.2425, 10.1575, 0.1],
			"rotation": {"angle": 22.5, "axis": "z", "origin": [7.125, 19.025, 0]},
			"faces": {
				"north": {"uv": [0, 1.43459, 12.76429, 6.33308], "rotation": 270, "texture": "#0"},
				"south": {"uv": [0.78222, 0.52211, 2.20444, 0.85895], "rotation": 90, "texture": "#0"},
				"up": {"uv": [0, 8.42105, 1.0621, 15.15789], "rotation": 90, "texture": "#0"}
			}
		},
		{
			"from": [14.825, 12.1, 0.125],
			"to": [14.925, 12.125, 0.225],
			"rotation": {"angle": 0, "axis": "z", "origin": [10.675, 17.525, -0.425]},
			"faces": {
				"north": {"uv": [1.06667, 0.23158, 1.13778, 0.26947], "rotation": 270, "texture": "#3"},
				"east": {"uv": [1.06667, 0.23158, 1.13778, 0.26947], "rotation": 90, "texture": "#3"},
				"south": {"uv": [1.06667, 0.23158, 1.13778, 0.26947], "rotation": 90, "texture": "#3"},
				"west": {"uv": [1.06667, 0.23158, 1.13778, 0.26947], "rotation": 90, "texture": "#3"},
				"up": {"uv": [1.06667, 0.23158, 1.13778, 0.26947], "rotation": 90, "texture": "#3"},
				"down": {"uv": [1.06667, 0.23158, 1.13778, 0.26947], "rotation": 90, "texture": "#3"}
			}
		},
		{
			"from": [14.825, 9.425, 0.125],
			"to": [14.925, 9.45, 0.225],
			"rotation": {"angle": 0, "axis": "z", "origin": [10.675, 14.85, -0.425]},
			"faces": {
				"north": {"uv": [1.06667, 0.23158, 1.13778, 0.26947], "rotation": 270, "texture": "#3"},
				"east": {"uv": [1.06667, 0.23158, 1.13778, 0.26947], "rotation": 90, "texture": "#3"},
				"south": {"uv": [1.06667, 0.23158, 1.13778, 0.26947], "rotation": 90, "texture": "#3"},
				"west": {"uv": [1.06667, 0.23158, 1.13778, 0.26947], "rotation": 90, "texture": "#3"},
				"up": {"uv": [1.06667, 0.23158, 1.13778, 0.26947], "rotation": 90, "texture": "#3"},
				"down": {"uv": [1.06667, 0.23158, 1.13778, 0.26947], "rotation": 90, "texture": "#3"}
			}
		},
		{
			"from": [14.85, 12.025, 0.15],
			"to": [14.9, 12.1, 0.2],
			"rotation": {"angle": 0, "axis": "z", "origin": [10.675, 17.525, -0.425]},
			"faces": {
				"north": {"uv": [1.06667, 0.23158, 1.13778, 0.26947], "rotation": 270, "texture": "#3"},
				"east": {"uv": [1.06667, 0.23158, 1.13778, 0.26947], "rotation": 90, "texture": "#3"},
				"south": {"uv": [1.06667, 0.23158, 1.13778, 0.26947], "rotation": 90, "texture": "#3"},
				"west": {"uv": [1.06667, 0.23158, 1.13778, 0.26947], "rotation": 90, "texture": "#3"}
			}
		},
		{
			"from": [14.85, 9.45, 0.15],
			"to": [14.9, 9.525, 0.2],
			"rotation": {"angle": 0, "axis": "z", "origin": [10.675, 14.95, -0.425]},
			"faces": {
				"north": {"uv": [1.06667, 0.23158, 1.13778, 0.26947], "rotation": 270, "texture": "#3"},
				"east": {"uv": [1.06667, 0.23158, 1.13778, 0.26947], "rotation": 90, "texture": "#3"},
				"south": {"uv": [1.06667, 0.23158, 1.13778, 0.26947], "rotation": 90, "texture": "#3"},
				"west": {"uv": [1.06667, 0.23158, 1.13778, 0.26947], "rotation": 90, "texture": "#3"}
			}
		}
	],
	"display": {
		"thirdperson_righthand": {
			"translation": [0, 3.75, 7.5]
		},
		"thirdperson_lefthand": {
			"translation": [0, 3.75, 7.5]
		},
		"fixed": {
			"translation": [0, 0, 8.5]
		}
	}
}